pickhost/__init__.py
pickhost/__main__.py
pickhost/pickhost.py
pickhost/system.py
pickhost-0.2.1.dist-info/LICENSE
pickhost-0.2.1.dist-info/METADATA
pickhost-0.2.1.dist-info/WHEEL
pickhost-0.2.1.dist-info/entry_points.txt
pickhost-0.2.1.dist-info/top_level.txt
pickhost-0.2.1.dist-info/RECORD
